{
  "activeOverrides": {
    "OVERRIDE_1760591099995_4814C754": {
      "id": "OVERRIDE_1760591099995_4814C754",
      "type": "emergency",
      "userId": "USER_1760591099651_FDDAC16C",
      "reason": "emergency_access",
      "timestamp": "2025-10-16T05:04:59.995Z",
      "expiresAt": "2025-10-16T05:19:59.995Z",
      "status": "expired",
      "additionalAuth": "account_access_emergency",
      "approvedBy": "SYSTEM_EMERGENCY_PROTOCOL",
      "notificationsSent": []
    },
    "OVERRIDE_1760591100339_D44EDFA4": {
      "id": "OVERRIDE_1760591100339_D44EDFA4",
      "type": "admin",
      "adminUserId": "admin@oscarsystem.com",
      "targetUserId": "USER_1760591100306_1956796D",
      "reason": "technical_issue",
      "justification": "User reported login issues",
      "timestamp": "2025-10-16T05:05:00.340Z",
      "expiresAt": "2025-10-16T05:20:00.340Z",
      "status": "expired",
      "approvedBy": "admin@oscarsystem.com",
      "notificationsSent": []
    }
  },
  "lastUpdated": "2025-10-16T05:24:57.690Z"
}